{
  "klass": "Specie",
  "id": 159,
  "dbSymbol": "mustorrent",
  "forms": [
    {
      "form": 0,
      "formTextId": {
        "name": 136,
        "description": 0
      },
      "height": 1.7,
      "weight": 46.8,
      "type1": "normal",
      "type2": "water",
      "baseHp": 65,
      "baseAtk": 100,
      "baseDfe": 65,
      "baseSpd": 120,
      "baseAts": 85,
      "baseDfs": 70,
      "evHp": 0,
      "evAtk": 0,
      "evDfe": 0,
      "evSpd": 2,
      "evAts": 0,
      "evDfs": 0,
      "evolutions": [],
      "experienceType": 1,
      "baseExperience": 170,
      "baseLoyalty": 70,
      "catchRate": 45,
      "femaleRate": 50,
      "breedGroups": [
        2,
        5
      ],
      "hatchSteps": 5120,
      "babyDbSymbol": "loutrogne",
      "babyForm": 0,
      "itemHeld": [
        {
          "dbSymbol": "none",
          "chance": 0
        },
        {
          "dbSymbol": "none",
          "chance": 0
        }
      ],
      "abilities": [
        "torrent",
        "water_veil",
        "swift_swim"
      ],
      "frontOffsetY": 0,
      "resources": {
        "icon": "159_i",
        "iconShiny": "159_i_s",
        "front": "159",
        "frontShiny": "159_s",
        "back": "159_b",
        "backShiny": "159_b_s",
        "footprint": "",
        "character": "159_c",
        "characterShiny": "159_c_s",
        "cry": "",
        "hasFemale": false,
        "egg": "egg",
        "iconEgg": "egg"
      },
      "moveSet": [
        {
          "klass": "LevelLearnableMove",
          "move": "water_gun",
          "level": 1
        },
        {
          "klass": "LevelLearnableMove",
          "move": "quick_attack",
          "level": 1
        },
        {
          "klass": "LevelLearnableMove",
          "move": "tail_whip",
          "level": 1
        },
        {
          "klass": "LevelLearnableMove",
          "move": "bite",
          "level": 3
        },
        {
          "klass": "LevelLearnableMove",
          "move": "aqua_jet",
          "level": 5
        },
        {
          "klass": "LevelLearnableMove",
          "move": "agility",
          "level": 9
        },
        {
          "klass": "LevelLearnableMove",
          "move": "slash",
          "level": 13
        },
        {
          "klass": "LevelLearnableMove",
          "move": "water_pulse",
          "level": 17
        },
        {
          "klass": "LevelLearnableMove",
          "move": "aqua_tail",
          "level": 21
        },
        {
          "klass": "LevelLearnableMove",
          "move": "double_hit",
          "level": 25
        },
        {
          "klass": "LevelLearnableMove",
          "move": "bounce",
          "level": 29
        },
        {
          "klass": "LevelLearnableMove",
          "move": "aqua_ring",
          "level": 33
        },
        {
          "klass": "LevelLearnableMove",
          "move": "crunch",
          "level": 37
        },
        {
          "klass": "LevelLearnableMove",
          "move": "hydro_pump",
          "level": 41
        },
        {
          "klass": "LevelLearnableMove",
          "move": "rain_dance",
          "level": 45
        },
        {
          "klass": "LevelLearnableMove",
          "move": "ice_fang",
          "level": 49
        },
        {
          "klass": "LevelLearnableMove",
          "move": "double_edge",
          "level": 53
        },
        {
          "klass": "LevelLearnableMove",
          "move": "hyper_voice",
          "level": 57
        },
        {
          "klass": "LevelLearnableMove",
          "move": "play_rough",
          "level": 61
        },
        {
          "klass": "LevelLearnableMove",
          "move": "scald",
          "level": 65
        },
        {
          "klass": "LevelLearnableMove",
          "move": "liquidation",
          "level": 69
        },
        {
          "klass": "LevelLearnableMove",
          "move": "giga_impact",
          "level": 73
        }
      ],
      "names": {
        "en": "Mustorrent",
        "fr": "Mustorrent",
        "it": "Croconaw",
        "de": "Tyracroc",
        "es": "Croconaw",
        "ko": "엘리게이"
      },
      "descriptions": {
        "en": "Excelling at swimming, Mustorrent's long body allows it to undulate for propulsion, reaching impressive speeds.",
        "fr": "Excellent nageur, le long corps de Mustorrent lui permet d'onduler afin de se propulser et atteindre des vitesses impressionnantes.",
        "it": "Una volta azzannato il nemico, Croconaw non molla la presa facilmente. Le zanne a punta ricurva all’indietro, a mo’ di amo da pesca, rendono impossibile estrarle quando sono conficcate in profondità.",
        "de": "Wenn Tyracroc einen Feind mit seinen Kiefern eingeklemmt hat, lässt es ihn nicht mehr los. Da seine Zahnspitzen wie Angelhaken gebogen sind, kann man sie nicht mehr entfernen, wenn sie sich verfangen haben.",
        "es": "Una vez que Croconaw le ha clavado los colmillos a su presa, es imposible que escape porque los tiene hacia adentro como si fueran anzuelos. Cuando Croconaw hinca los dientes, no hay escapatoria.",
        "ko": "한 번 물고 늘어지면 절대로 놓지 않는다. 이빨 끝이 낚싯바늘처럼 휘어져 있어서 한 번 들어가면 빠지지 않는다."
      },
      "abilities_data": [
        {
          "symbol": "torrent",
          "textId": 67,
          "names": {
            "en": "Torrent",
            "fr": "Torrent",
            "it": "Acquaiuto",
            "de": "Sturzbach",
            "es": "Torrente",
            "ko": "급류"
          },
          "descriptions": {
            "en": "Powers up Water-type moves when the Pokémon’s HP is low.",
            "fr": "Augmente la puissance des capacités de type Eau du Pokémon quand il a perdu une certaine quantité de PV.",
            "it": "Quando il Pokémon ha pochi PS, la potenza delle sue mosse di tipo Acqua aumenta.",
            "de": "Erhöht die Stärke von Wasser-Attacken, wenn die KP auf einen gewissen Wert fallen.",
            "es": "Potencia sus movimientos de tipo Agua cuando le quedan pocos PS.",
            "ko": "HP가 줄었을 때 물타입 기술의 위력이 올라간다."
          }
        },
        {
          "symbol": "water_veil",
          "textId": 41,
          "names": {
            "en": "Water Veil",
            "fr": "Ignifu-Voile",
            "it": "Idrovelo",
            "de": "Aquahülle",
            "es": "Velo Agua",
            "ko": "수의베일"
          },
          "descriptions": {
            "en": "The Pokémon is covered with a water veil, which prevents the Pokémon from getting a burn.",
            "fr": "Le voile qui recouvre le Pokémon le protège des brûlures.",
            "it": "Un velo d’acqua riveste il corpo del Pokémon impedendogli di venire scottato.",
            "de": "Verhindert durch eine Hülle aus Wasser Verbrennungen.",
            "es": "Evita las quemaduras gracias a la capa de agua que lo envuelve.",
            "ko": "물의 베일을 몸에 둘러서 화상 상태가 되지 않는다."
          }
        },
        {
          "symbol": "swift_swim",
          "textId": 33,
          "names": {
            "en": "Swift Swim",
            "fr": "Glissade",
            "it": "Nuotovelox",
            "de": "Wassertempo",
            "es": "Nado Rápido",
            "ko": "쓱쓱"
          },
          "descriptions": {
            "en": "Boosts the Pokémon’s Speed stat in rain.",
            "fr": "Augmente la Vitesse du Pokémon s’il pleut.",
            "it": "Se piove, la Velocità aumenta.",
            "de": "Erhöht bei Regen die Initiative.",
            "es": "Sube su Velocidad cuando llueve.",
            "ko": "비가 오는 날씨일 때 스피드가 올라간다."
          }
        }
      ],
      "moves_data": [
        {
          "symbol": "water_gun",
          "id": 55,
          "klass": "LevelLearnableMove",
          "level": 1,
          "names": {
            "en": "Water Gun",
            "fr": "Pistolet à O",
            "it": "Pistolacqua",
            "de": "Aquaknarre",
            "es": "Pistola Agua",
            "ko": "물대포"
          },
          "category": "special",
          "type": "water",
          "pp": 25,
          "power": 40,
          "accuracy": 100
        },
        {
          "symbol": "quick_attack",
          "id": 98,
          "klass": "LevelLearnableMove",
          "level": 1,
          "names": {
            "en": "Quick Attack",
            "fr": "Vive-Attaque",
            "it": "Attacco Rapido",
            "de": "Ruckzuckhieb",
            "es": "Ataque Rápido",
            "ko": "전광석화"
          },
          "category": "physical",
          "type": "normal",
          "pp": 30,
          "power": 40,
          "accuracy": 100
        },
        {
          "symbol": "tail_whip",
          "id": 39,
          "klass": "LevelLearnableMove",
          "level": 1,
          "names": {
            "en": "Tail Whip",
            "fr": "Mimi-Queue",
            "it": "Colpocoda",
            "de": "Rutenschlag",
            "es": "Látigo",
            "ko": "꼬리흔들기"
          },
          "category": "status",
          "type": "normal",
          "pp": 30,
          "power": 0,
          "accuracy": 100
        },
        {
          "symbol": "bite",
          "id": 44,
          "klass": "LevelLearnableMove",
          "level": 3,
          "names": {
            "en": "Bite",
            "fr": "Morsure",
            "it": "Morso",
            "de": "Biss",
            "es": "Mordisco",
            "ko": "물기"
          },
          "category": "physical",
          "type": "dark",
          "pp": 25,
          "power": 60,
          "accuracy": 100
        },
        {
          "symbol": "aqua_jet",
          "id": 453,
          "klass": "LevelLearnableMove",
          "level": 5,
          "names": {
            "en": "Aqua Jet",
            "fr": "Aqua-Jet",
            "it": "Acquagetto",
            "de": "Wasserdüse",
            "es": "Acua Jet",
            "ko": "아쿠아제트"
          },
          "category": "physical",
          "type": "water",
          "pp": 20,
          "power": 40,
          "accuracy": 100
        },
        {
          "symbol": "agility",
          "id": 97,
          "klass": "LevelLearnableMove",
          "level": 9,
          "names": {
            "en": "Agility",
            "fr": "Hâte",
            "it": "Agilità",
            "de": "Agilität",
            "es": "Agilidad",
            "ko": "고속이동"
          },
          "category": "status",
          "type": "psychic",
          "pp": 30,
          "power": 0,
          "accuracy": 0
        },
        {
          "symbol": "slash",
          "id": 163,
          "klass": "LevelLearnableMove",
          "level": 13,
          "names": {
            "en": "Slash",
            "fr": "Tranche",
            "it": "Lacerazione",
            "de": "Schlitzer",
            "es": "Cuchillada",
            "ko": "베어가르기"
          },
          "category": "physical",
          "type": "normal",
          "pp": 20,
          "power": 70,
          "accuracy": 100
        },
        {
          "symbol": "water_pulse",
          "id": 352,
          "klass": "LevelLearnableMove",
          "level": 17,
          "names": {
            "en": "Water Pulse",
            "fr": "Vibraqua",
            "it": "Idropulsar",
            "de": "Aquawelle",
            "es": "Hidropulso",
            "ko": "물의파동"
          },
          "category": "special",
          "type": "water",
          "pp": 20,
          "power": 60,
          "accuracy": 100
        },
        {
          "symbol": "aqua_tail",
          "id": 401,
          "klass": "LevelLearnableMove",
          "level": 21,
          "names": {
            "en": "Aqua Tail",
            "fr": "Hydro-Queue",
            "it": "Idrondata",
            "de": "Nassschweif",
            "es": "Acua Cola",
            "ko": "아쿠아테일"
          },
          "category": "physical",
          "type": "water",
          "pp": 10,
          "power": 90,
          "accuracy": 90
        },
        {
          "symbol": "double_hit",
          "id": 458,
          "klass": "LevelLearnableMove",
          "level": 25,
          "names": {
            "en": "Double Hit",
            "fr": "Coup Double",
            "it": "Doppiosmash",
            "de": "Doppelschlag",
            "es": "Doble Golpe",
            "ko": "더블어택"
          },
          "category": "physical",
          "type": "normal",
          "pp": 10,
          "power": 35,
          "accuracy": 90
        },
        {
          "symbol": "bounce",
          "id": 340,
          "klass": "LevelLearnableMove",
          "level": 29,
          "names": {
            "en": "Bounce",
            "fr": "Rebond",
            "it": "Rimbalzo",
            "de": "Sprungfeder",
            "es": "Bote",
            "ko": "뛰어오르다"
          },
          "category": "physical",
          "type": "flying",
          "pp": 5,
          "power": 85,
          "accuracy": 85
        },
        {
          "symbol": "aqua_ring",
          "id": 392,
          "klass": "LevelLearnableMove",
          "level": 33,
          "names": {
            "en": "Aqua Ring",
            "fr": "Anneau Hydro",
            "it": "Acquanello",
            "de": "Wasserring",
            "es": "Acua Aro",
            "ko": "아쿠아링"
          },
          "category": "status",
          "type": "water",
          "pp": 20,
          "power": 0,
          "accuracy": 0
        },
        {
          "symbol": "crunch",
          "id": 242,
          "klass": "LevelLearnableMove",
          "level": 37,
          "names": {
            "en": "Crunch",
            "fr": "Mâchouille",
            "it": "Sgranocchio",
            "de": "Knirscher",
            "es": "Triturar",
            "ko": "깨물어부수기"
          },
          "category": "physical",
          "type": "dark",
          "pp": 15,
          "power": 80,
          "accuracy": 100
        },
        {
          "symbol": "hydro_pump",
          "id": 56,
          "klass": "LevelLearnableMove",
          "level": 41,
          "names": {
            "en": "Hydro Pump",
            "fr": "Hydrocanon",
            "it": "Idropompa",
            "de": "Hydropumpe",
            "es": "Hidrobomba",
            "ko": "하이드로펌프"
          },
          "category": "special",
          "type": "water",
          "pp": 5,
          "power": 110,
          "accuracy": 80
        },
        {
          "symbol": "rain_dance",
          "id": 240,
          "klass": "LevelLearnableMove",
          "level": 45,
          "names": {
            "en": "Rain Dance",
            "fr": "Danse Pluie",
            "it": "Pioggiadanza",
            "de": "Regentanz",
            "es": "Danza Lluvia",
            "ko": "비바라기"
          },
          "category": "status",
          "type": "water",
          "pp": 5,
          "power": 0,
          "accuracy": 0
        },
        {
          "symbol": "ice_fang",
          "id": 423,
          "klass": "LevelLearnableMove",
          "level": 49,
          "names": {
            "en": "Ice Fang",
            "fr": "Crocs Givre",
            "it": "Gelodenti",
            "de": "Eiszahn",
            "es": "Colmillo Hielo",
            "ko": "얼음엄니"
          },
          "category": "physical",
          "type": "ice",
          "pp": 15,
          "power": 65,
          "accuracy": 95
        },
        {
          "symbol": "double_edge",
          "id": 38,
          "klass": "LevelLearnableMove",
          "level": 53,
          "names": {
            "en": "Double-Edge",
            "fr": "Damoclès",
            "it": "Sdoppiatore",
            "de": "Risikotackle",
            "es": "Doble Filo",
            "ko": "이판사판태클"
          },
          "category": "physical",
          "type": "normal",
          "pp": 15,
          "power": 120,
          "accuracy": 100
        },
        {
          "symbol": "hyper_voice",
          "id": 304,
          "klass": "LevelLearnableMove",
          "level": 57,
          "names": {
            "en": "Hyper Voice",
            "fr": "Mégaphone",
            "it": "Granvoce",
            "de": "Schallwelle",
            "es": "Vozarrón",
            "ko": "하이퍼보이스"
          },
          "category": "special",
          "type": "normal",
          "pp": 10,
          "power": 90,
          "accuracy": 100
        },
        {
          "symbol": "play_rough",
          "id": 583,
          "klass": "LevelLearnableMove",
          "level": 61,
          "names": {
            "en": "Play Rough",
            "fr": "Câlinerie",
            "it": "Carineria",
            "de": "Knuddler",
            "es": "Carantoña",
            "ko": "치근거리기"
          },
          "category": "physical",
          "type": "fairy",
          "pp": 10,
          "power": 90,
          "accuracy": 90
        },
        {
          "symbol": "scald",
          "id": 503,
          "klass": "LevelLearnableMove",
          "level": 65,
          "names": {
            "en": "Scald",
            "fr": "Ébullition",
            "it": "Idrovampata",
            "de": "Siedewasser",
            "es": "Escaldar",
            "ko": "열탕"
          },
          "category": "special",
          "type": "water",
          "pp": 15,
          "power": 80,
          "accuracy": 100
        },
        {
          "symbol": "liquidation",
          "id": 710,
          "klass": "LevelLearnableMove",
          "level": 69,
          "names": {
            "en": "Liquidation",
            "fr": "Aqua-Brèche",
            "it": "Idrobreccia",
            "de": "Aquadurchstoß",
            "es": "Hidroariete",
            "ko": "아쿠아브레이크"
          },
          "category": "physical",
          "type": "water",
          "pp": 10,
          "power": 85,
          "accuracy": 100
        },
        {
          "symbol": "giga_impact",
          "id": 416,
          "klass": "LevelLearnableMove",
          "level": 73,
          "names": {
            "en": "Giga Impact",
            "fr": "Giga Impact",
            "it": "Gigaimpatto",
            "de": "Gigastoß",
            "es": "Gigaimpacto",
            "ko": "기가임팩트"
          },
          "category": "physical",
          "type": "normal",
          "pp": 5,
          "power": 150,
          "accuracy": 90
        }
      ]
    }
  ]
}